beardataclass-0.2.1.dist-info/METADATA
beardataclass-0.2.1.dist-info/WHEEL
beardataclass/__init__.py
beardataclass/cls.py
beardataclass-0.2.1.dist-info/RECORD
