Metadata-Version: 2.1
Name: BearDataClass
Version: 0.2.1
Home-page: https://github.com/cgebbe/beardataclass
Author: Christian Gebbe
License: MIT
Project-URL: Homepage, https://github.com/cgebbe/beardataclass
Requires-Python: >=3.8
Requires-Dist: pandas
